{
  "$schema": "http://json-schema.org/draft-07/schema#",
  "screenName": "Individual Blog Post Page",
  "screenId": "blog-post-001",
  "version": "2.0.1",
  "designSystem": "Premium Dark Glassmorphism + MUI + MDX",
  "description": "Updated to include standardized navbar-v2 component",
  "viewport": {
    "mobile": "375x812",
    "tablet": "768x1024",
    "desktop": "1440x900"
  },
  "layout": {
    "type": "article-with-sidebar",
    "background": "#06080f",
    "sections": [
      {
        "id": "navbar",
        "componentRef": "navbar-v2",
        "componentPath": "wireframes/components/navbar.json",
        "activeItem": "Blog",
        "note": "Fixed centered glass navbar - Blog is highlighted as this is a blog post"
      },
      {
        "id": "post-hero",
        "component": "Box",
        "muiComponent": "Box",
        "styling": {
          "position": "relative",
          "height": "500px",
          "overflow": "hidden",
          "marginBottom": "64px"
        },
        "content": {
          "backgroundImage": {
            "component": "Box",
            "styling": {
              "position": "absolute",
              "top": 0,
              "left": 0,
              "right": 0,
              "bottom": 0,
              "backgroundImage": "url('/blog/post-hero.jpg')",
              "backgroundSize": "cover",
              "backgroundPosition": "center",
              "filter": "brightness(0.7)"
            }
          },
          "gradientOverlay": {
            "component": "Box",
            "styling": {
              "position": "absolute",
              "top": 0,
              "left": 0,
              "right": 0,
              "bottom": 0,
              "background": "linear-gradient(180deg, rgba(0,0,0,0.3) 0%, rgba(0,0,0,0.7) 100%)"
            }
          },
          "heroContent": {
            "component": "Container",
            "maxWidth": "md",
            "styling": {
              "position": "relative",
              "height": "100%",
              "display": "flex",
              "flexDirection": "column",
              "justifyContent": "flex-end",
              "paddingBottom": "48px",
              "zIndex": 1
            },
            "elements": [
              {
                "component": "Chip",
                "label": "Product Management",
                "styling": {
                  "background": "rgba(255, 255, 255, 0.25)",
                  "backdropFilter": "blur(10px)",
                  "color": "#fff",
                  "fontWeight": 600,
                  "marginBottom": "16px",
                  "border": "1px solid rgba(255, 255, 255, 0.3)"
                }
              },
              {
                "component": "Typography",
                "variant": "h1",
                "text": "Building Products Users Love: Lessons from StartHub",
                "styling": {
                  "color": "#fff",
                  "fontWeight": 800,
                  "fontSize": {
                    "mobile": "2rem",
                    "tablet": "2.75rem",
                    "desktop": "3.5rem"
                  },
                  "marginBottom": "24px",
                  "textShadow": "0 2px 8px rgba(0,0,0,0.3)"
                }
              },
              {
                "component": "Box",
                "display": "flex",
                "alignItems": "center",
                "gap": 3,
                "flexWrap": "wrap",
                "metadata": [
                  {
                    "component": "Box",
                    "display": "flex",
                    "alignItems": "center",
                    "gap": 1.5,
                    "content": {
                      "avatar": {
                        "component": "Avatar",
                        "src": "/author-avatar.jpg",
                        "alt": "Ronnie Lutaro",
                        "size": 40
                      },
                      "authorName": {
                        "component": "Typography",
                        "variant": "body1",
                        "text": "Ronnie Lutaro",
                        "styling": {
                          "color": "#fff",
                          "fontWeight": 600
                        }
                      }
                    }
                  },
                  {
                    "component": "Typography",
                    "variant": "body2",
                    "text": "•",
                    "styling": {
                      "color": "rgba(255, 255, 255, 0.7)"
                    }
                  },
                  {
                    "component": "Box",
                    "display": "flex",
                    "alignItems": "center",
                    "gap": 0.5,
                    "content": {
                      "icon": {
                        "component": "SvgIcon",
                        "icon": "CalendarTodayOutlined",
                        "fontSize": "small",
                        "styling": {
                          "color": "rgba(255, 255, 255, 0.9)"
                        }
                      },
                      "text": {
                        "component": "Typography",
                        "variant": "body2",
                        "text": "October 9, 2025",
                        "styling": {
                          "color": "rgba(255, 255, 255, 0.9)"
                        }
                      }
                    }
                  },
                  {
                    "component": "Typography",
                    "variant": "body2",
                    "text": "•",
                    "styling": {
                      "color": "rgba(255, 255, 255, 0.7)"
                    }
                  },
                  {
                    "component": "Box",
                    "display": "flex",
                    "alignItems": "center",
                    "gap": 0.5,
                    "content": {
                      "icon": {
                        "component": "SvgIcon",
                        "icon": "AccessTimeOutlined",
                        "fontSize": "small",
                        "styling": {
                          "color": "rgba(255, 255, 255, 0.9)"
                        }
                      },
                      "text": {
                        "component": "Typography",
                        "variant": "body2",
                        "text": "5 min read",
                        "styling": {
                          "color": "rgba(255, 255, 255, 0.9)"
                        }
                      }
                    }
                  }
                ]
              }
            ]
          }
        }
      },
      {
        "id": "progress-bar",
        "component": "LinearProgress",
        "muiComponent": "LinearProgress",
        "variant": "determinate",
        "value": 0,
        "styling": {
          "position": "fixed",
          "top": "64px",
          "left": 0,
          "right": 0,
          "zIndex": 1200,
          "height": "3px",
          "background": "transparent",
          "bar": {
            "background": "linear-gradient(90deg, #667eea 0%, #764ba2 100%)"
          }
        },
        "behavior": "updates-on-scroll"
      },
      {
        "id": "article-content-wrapper",
        "component": "Container",
        "maxWidth": "xl",
        "styling": {
          "paddingBottom": "80px"
        },
        "content": {
          "grid": {
            "component": "Grid",
            "container": true,
            "spacing": 4,
            "columns": [
              {
                "id": "table-of-contents-sidebar",
                "gridItem": {
                  "xs": 12,
                  "lg": 3
                },
                "display": {
                  "xs": "none",
                  "lg": "block"
                },
                "content": {
                  "stickyContainer": {
                    "component": "Box",
                    "styling": {
                      "position": "sticky",
                      "top": "100px"
                    },
                    "card": {
                      "component": "Card",
                      "styling": {
                        "background": "rgba(255, 255, 255, 0.6)",
                        "backdropFilter": "blur(20px)",
                        "borderRadius": "16px",
                        "border": "1px solid rgba(255, 255, 255, 0.18)",
                        "padding": "24px"
                      },
                      "content": {
                        "title": {
                          "component": "Typography",
                          "variant": "subtitle2",
                          "text": "TABLE OF CONTENTS",
                          "styling": {
                            "fontWeight": 700,
                            "marginBottom": "16px",
                            "color": "text.secondary",
                            "letterSpacing": "0.5px"
                          }
                        },
                        "tocList": {
                          "component": "List",
                          "muiComponent": "List",
                          "dense": true,
                          "items": [
                            {
                              "component": "ListItemButton",
                              "muiComponent": "ListItemButton",
                              "selected": true,
                              "onClick": "scroll-to-heading-1",
                              "styling": {
                                "borderRadius": "8px",
                                "marginBottom": "4px",
                                "selected": {
                                  "background": "rgba(102, 126, 234, 0.15)",
                                  "borderLeft": "3px solid #667eea"
                                }
                              },
                              "content": {
                                "text": {
                                  "component": "ListItemText",
                                  "primary": "Introduction",
                                  "primaryTypographyProps": {
                                    "variant": "body2",
                                    "fontWeight": 500
                                  }
                                }
                              }
                            },
                            {
                              "component": "ListItemButton",
                              "content": {
                                "text": {
                                  "primary": "Customer Discovery Process"
                                }
                              }
                            },
                            {
                              "component": "ListItemButton",
                              "content": {
                                "text": {
                                  "primary": "Translating Insights to Features"
                                }
                              }
                            },
                            {
                              "component": "ListItemButton",
                              "content": {
                                "text": {
                                  "primary": "Post-Launch Iteration"
                                }
                              }
                            },
                            {
                              "component": "ListItemButton",
                              "content": {
                                "text": {
                                  "primary": "Key Takeaways"
                                }
                              }
                            }
                          ]
                        }
                      }
                    }
                  }
                }
              },
              {
                "id": "main-article-content",
                "gridItem": {
                  "xs": 12,
                  "lg": 6
                },
                "content": {
                  "articleCard": {
                    "component": "Card",
                    "styling": {
                      "background": "rgba(255, 255, 255, 0.8)",
                      "backdropFilter": "blur(20px)",
                      "borderRadius": "20px",
                      "border": "1px solid rgba(255, 255, 255, 0.18)",
                      "padding": {
                        "mobile": "24px",
                        "tablet": "40px",
                        "desktop": "48px"
                      }
                    },
                    "content": {
                      "mdxContent": {
                        "component": "MDXContent",
                        "styling": {
                          "h2": {
                            "fontWeight": 700,
                            "fontSize": "2rem",
                            "marginTop": "48px",
                            "marginBottom": "16px",
                            "color": "text.primary",
                            "scrollMarginTop": "100px"
                          },
                          "h3": {
                            "fontWeight": 600,
                            "fontSize": "1.5rem",
                            "marginTop": "32px",
                            "marginBottom": "12px",
                            "scrollMarginTop": "100px"
                          },
                          "p": {
                            "fontSize": "1.125rem",
                            "lineHeight": 1.8,
                            "marginBottom": "24px",
                            "color": "text.primary"
                          },
                          "a": {
                            "color": "primary.main",
                            "textDecoration": "underline",
                            "textUnderlineOffset": "3px",
                            "hover": {
                              "color": "primary.dark"
                            }
                          },
                          "ul": {
                            "marginBottom": "24px",
                            "paddingLeft": "24px"
                          },
                          "li": {
                            "fontSize": "1.125rem",
                            "lineHeight": 1.8,
                            "marginBottom": "8px"
                          },
                          "blockquote": {
                            "borderLeft": "4px solid",
                            "borderColor": "primary.main",
                            "paddingLeft": "24px",
                            "marginLeft": 0,
                            "marginBottom": "24px",
                            "fontStyle": "italic",
                            "color": "text.secondary",
                            "background": "rgba(102, 126, 234, 0.05)",
                            "padding": "16px 24px",
                            "borderRadius": "0 8px 8px 0"
                          },
                          "code": {
                            "fontFamily": "monospace",
                            "fontSize": "0.9em",
                            "background": "rgba(0, 0, 0, 0.05)",
                            "padding": "2px 6px",
                            "borderRadius": "4px",
                            "color": "#e83e8c"
                          },
                          "pre": {
                            "background": "rgba(30, 30, 30, 0.95)",
                            "backdropFilter": "blur(10px)",
                            "borderRadius": "12px",
                            "padding": "24px",
                            "marginBottom": "24px",
                            "overflow": "auto",
                            "position": "relative",
                            "border": "1px solid rgba(255, 255, 255, 0.1)"
                          },
                          "pre code": {
                            "background": "transparent",
                            "padding": 0,
                            "color": "#f8f8f2",
                            "fontSize": "0.95rem",
                            "lineHeight": 1.6
                          },
                          "img": {
                            "maxWidth": "100%",
                            "height": "auto",
                            "borderRadius": "12px",
                            "marginBottom": "24px",
                            "cursor": "zoom-in"
                          }
                        },
                        "customComponents": {
                          "CodeBlock": {
                            "description": "Syntax highlighted code with copy button",
                            "features": [
                              "Language indicator",
                              "Copy to clipboard button",
                              "Line numbers (optional)",
                              "Syntax highlighting"
                            ]
                          },
                          "Callout": {
                            "variants": [
                              "info",
                              "warning",
                              "success",
                              "error"
                            ],
                            "styling": {
                              "background": "glassmorphic",
                              "borderRadius": "12px",
                              "padding": "16px",
                              "marginBottom": "24px",
                              "icon": "variant-specific"
                            }
                          },
                          "ImageZoom": {
                            "description": "Clickable images with lightbox",
                            "features": [
                              "Click to zoom",
                              "Caption support",
                              "Close on outside click"
                            ]
                          }
                        }
                      }
                    }
                  }
                }
              },
              {
                "id": "social-share-sidebar",
                "gridItem": {
                  "xs": 12,
                  "lg": 3
                },
                "display": {
                  "xs": "none",
                  "lg": "block"
                },
                "content": {
                  "stickyContainer": {
                    "component": "Box",
                    "styling": {
                      "position": "sticky",
                      "top": "100px"
                    },
                    "card": {
                      "component": "Card",
                      "styling": {
                        "background": "rgba(255, 255, 255, 0.6)",
                        "backdropFilter": "blur(20px)",
                        "borderRadius": "16px",
                        "border": "1px solid rgba(255, 255, 255, 0.18)",
                        "padding": "24px",
                        "textAlign": "center"
                      },
                      "content": {
                        "title": {
                          "component": "Typography",
                          "variant": "subtitle2",
                          "text": "SHARE THIS POST",
                          "styling": {
                            "fontWeight": 700,
                            "marginBottom": "16px",
                            "color": "text.secondary",
                            "letterSpacing": "0.5px"
                          }
                        },
                        "shareButtons": {
                          "component": "Box",
                          "display": "flex",
                          "flexDirection": "column",
                          "gap": 1.5,
                          "buttons": [
                            {
                              "component": "Button",
                              "muiComponent": "Button",
                              "variant": "outlined",
                              "fullWidth": true,
                              "startIcon": "Twitter",
                              "text": "Twitter",
                              "onClick": "share-to-twitter",
                              "styling": {
                                "borderRadius": "12px",
                                "textTransform": "none",
                                "justifyContent": "flex-start",
                                "borderColor": "rgba(29, 161, 242, 0.3)",
                                "color": "#1DA1F2",
                                "hover": {
                                  "background": "rgba(29, 161, 242, 0.1)",
                                  "borderColor": "#1DA1F2"
                                }
                              }
                            },
                            {
                              "component": "Button",
                              "variant": "outlined",
                              "fullWidth": true,
                              "startIcon": "LinkedIn",
                              "text": "LinkedIn",
                              "onClick": "share-to-linkedin",
                              "styling": {
                                "borderRadius": "12px",
                                "textTransform": "none",
                                "justifyContent": "flex-start",
                                "borderColor": "rgba(0, 119, 181, 0.3)",
                                "color": "#0077B5",
                                "hover": {
                                  "background": "rgba(0, 119, 181, 0.1)",
                                  "borderColor": "#0077B5"
                                }
                              }
                            },
                            {
                              "component": "Button",
                              "variant": "outlined",
                              "fullWidth": true,
                              "startIcon": "Link",
                              "text": "Copy Link",
                              "onClick": "copy-link-to-clipboard",
                              "styling": {
                                "borderRadius": "12px",
                                "textTransform": "none",
                                "justifyContent": "flex-start",
                                "borderColor": "rgba(102, 126, 234, 0.3)",
                                "color": "#667eea",
                                "hover": {
                                  "background": "rgba(102, 126, 234, 0.1)",
                                  "borderColor": "#667eea"
                                }
                              }
                            }
                          ]
                        },
                        "divider": {
                          "component": "Divider",
                          "styling": {
                            "margin": "24px 0"
                          }
                        },
                        "tags": {
                          "title": {
                            "component": "Typography",
                            "variant": "subtitle2",
                            "text": "TAGS",
                            "styling": {
                              "fontWeight": 700,
                              "marginBottom": "12px",
                              "color": "text.secondary"
                            }
                          },
                          "chipGroup": {
                            "component": "Box",
                            "display": "flex",
                            "flexWrap": "wrap",
                            "gap": 1,
                            "justifyContent": "center",
                            "chips": [
                              {
                                "component": "Chip",
                                "label": "Product",
                                "size": "small",
                                "clickable": true,
                                "onClick": "filter-by-tag"
                              },
                              {
                                "component": "Chip",
                                "label": "Strategy",
                                "size": "small",
                                "clickable": true
                              },
                              {
                                "component": "Chip",
                                "label": "StartHub",
                                "size": "small",
                                "clickable": true
                              }
                            ]
                          }
                        }
                      }
                    }
                  }
                }
              }
            ]
          }
        }
      },
      {
        "id": "mobile-share-actions",
        "component": "Box",
        "display": {
          "xs": "block",
          "lg": "none"
        },
        "styling": {
          "position": "fixed",
          "bottom": 0,
          "left": 0,
          "right": 0,
          "background": "rgba(255, 255, 255, 0.95)",
          "backdropFilter": "blur(20px)",
          "borderTop": "1px solid rgba(0, 0, 0, 0.08)",
          "padding": "12px 16px",
          "zIndex": 1100,
          "display": "flex",
          "gap": 1,
          "justifyContent": "space-around"
        },
        "content": {
          "shareButtons": [
            {
              "component": "IconButton",
              "icon": "Twitter",
              "ariaLabel": "Share on Twitter",
              "color": "primary"
            },
            {
              "component": "IconButton",
              "icon": "LinkedIn",
              "ariaLabel": "Share on LinkedIn",
              "color": "primary"
            },
            {
              "component": "IconButton",
              "icon": "Link",
              "ariaLabel": "Copy link",
              "color": "primary"
            }
          ]
        }
      },
      {
        "id": "author-bio-section",
        "component": "Container",
        "maxWidth": "md",
        "styling": {
          "marginTop": "80px",
          "marginBottom": "64px"
        },
        "content": {
          "card": {
            "component": "Card",
            "styling": {
              "background": "linear-gradient(135deg, rgba(102, 126, 234, 0.1) 0%, rgba(118, 75, 162, 0.1) 100%)",
              "backdropFilter": "blur(20px)",
              "borderRadius": "20px",
              "border": "1px solid rgba(255, 255, 255, 0.18)",
              "padding": "32px"
            },
            "content": {
              "grid": {
                "component": "Grid",
                "container": true,
                "spacing": 3,
                "alignItems": "center",
                "columns": [
                  {
                    "gridItem": {
                      "xs": 12,
                      "sm": "auto"
                    },
                    "content": {
                      "avatar": {
                        "component": "Avatar",
                        "src": "/author-avatar.jpg",
                        "alt": "Ronnie Lutaro",
                        "styling": {
                          "width": 100,
                          "height": 100,
                          "border": "3px solid rgba(102, 126, 234, 0.3)",
                          "boxShadow": "0 4px 12px rgba(0, 0, 0, 0.1)"
                        }
                      }
                    }
                  },
                  {
                    "gridItem": {
                      "xs": 12,
                      "sm": true
                    },
                    "content": {
                      "title": {
                        "component": "Typography",
                        "variant": "h6",
                        "text": "About the Author",
                        "styling": {
                          "fontWeight": 700,
                          "marginBottom": "8px"
                        }
                      },
                      "name": {
                        "component": "Typography",
                        "variant": "subtitle1",
                        "text": "Ronnie Lutaro",
                        "styling": {
                          "fontWeight": 600,
                          "color": "primary.main",
                          "marginBottom": "8px"
                        }
                      },
                      "bio": {
                        "component": "Typography",
                        "variant": "body2",
                        "text": "Product Manager with 4+ years of product work and a software engineering background. I translate user needs into Products they deeply love and care about.",
                        "styling": {
                          "color": "text.secondary",
                          "lineHeight": 1.6,
                          "marginBottom": "12px"
                        }
                      },
                      "socialLinks": {
                        "component": "Box",
                        "display": "flex",
                        "gap": 1,
                        "buttons": [
                          {
                            "component": "IconButton",
                            "size": "small",
                            "icon": "LinkedIn",
                            "ariaLabel": "LinkedIn profile"
                          },
                          {
                            "component": "IconButton",
                            "size": "small",
                            "icon": "GitHub",
                            "ariaLabel": "GitHub profile"
                          },
                          {
                            "component": "IconButton",
                            "size": "small",
                            "icon": "Twitter",
                            "ariaLabel": "Twitter profile"
                          }
                        ]
                      }
                    }
                  }
                ]
              }
            }
          }
        }
      },
      {
        "id": "related-posts-section",
        "component": "Container",
        "maxWidth": "lg",
        "styling": {
          "marginBottom": "64px"
        },
        "content": {
          "title": {
            "component": "Typography",
            "variant": "h4",
            "text": "Related Posts",
            "styling": {
              "fontWeight": 700,
              "marginBottom": "32px",
              "textAlign": "center"
            }
          },
          "grid": {
            "component": "Grid",
            "container": true,
            "spacing": 3,
            "posts": [
              {
                "gridItem": {
                  "xs": 12,
                  "md": 4
                },
                "card": {
                  "component": "Card",
                  "note": "Same structure as blog listing cards",
                  "styling": {
                    "background": "rgba(255, 255, 255, 0.7)",
                    "backdropFilter": "blur(20px)",
                    "borderRadius": "16px",
                    "cursor": "pointer",
                    "transition": "all 0.3s",
                    "hover": {
                      "transform": "translateY(-4px)",
                      "boxShadow": "0 12px 24px rgba(0, 0, 0, 0.1)"
                    }
                  }
                }
              }
            ],
            "note": "Show 3 related posts"
          }
        }
      },
      {
        "id": "newsletter-cta-section",
        "component": "Container",
        "maxWidth": "md",
        "styling": {
          "marginBottom": "64px"
        },
        "content": {
          "card": {
            "component": "Card",
            "styling": {
              "background": "linear-gradient(135deg, rgba(102, 126, 234, 0.15) 0%, rgba(118, 75, 162, 0.15) 100%)",
              "backdropFilter": "blur(30px)",
              "borderRadius": "24px",
              "border": "1px solid rgba(255, 255, 255, 0.18)",
              "padding": "48px",
              "textAlign": "center"
            },
            "content": {
              "title": {
                "component": "Typography",
                "variant": "h4",
                "text": "Enjoyed this post?",
                "styling": {
                  "fontWeight": 700,
                  "marginBottom": "12px"
                }
              },
              "subtitle": {
                "component": "Typography",
                "variant": "body1",
                "text": "Subscribe to get more insights like this delivered to your inbox",
                "styling": {
                  "color": "text.secondary",
                  "marginBottom": "32px"
                }
              },
              "form": {
                "component": "Box",
                "display": "flex",
                "gap": 2,
                "maxWidth": "500px",
                "margin": "0 auto",
                "flexDirection": {
                  "xs": "column",
                  "sm": "row"
                },
                "elements": [
                  {
                    "component": "TextField",
                    "type": "email",
                    "placeholder": "Your email",
                    "variant": "outlined",
                    "fullWidth": true,
                    "styling": {
                      "background": "rgba(255, 255, 255, 0.9)",
                      "borderRadius": "12px"
                    }
                  },
                  {
                    "component": "Button",
                    "variant": "contained",
                    "size": "large",
                    "text": "Subscribe",
                    "styling": {
                      "background": "linear-gradient(45deg, #667eea 30%, #764ba2 90%)",
                      "borderRadius": "12px",
                      "padding": "12px 32px",
                      "textTransform": "none",
                      "fontWeight": 600,
                      "whiteSpace": "nowrap"
                    }
                  }
                ]
              }
            }
          }
        }
      },
      {
        "id": "prev-next-navigation",
        "component": "Container",
        "maxWidth": "md",
        "styling": {
          "marginBottom": "80px"
        },
        "content": {
          "grid": {
            "component": "Grid",
            "container": true,
            "spacing": 2,
            "navigation": [
              {
                "gridItem": {
                  "xs": 12,
                  "sm": 6
                },
                "button": {
                  "component": "Card",
                  "clickable": true,
                  "styling": {
                    "background": "rgba(255, 255, 255, 0.6)",
                    "backdropFilter": "blur(20px)",
                    "borderRadius": "16px",
                    "padding": "20px",
                    "cursor": "pointer",
                    "transition": "all 0.3s",
                    "hover": {
                      "background": "rgba(255, 255, 255, 0.8)",
                      "transform": "translateX(-4px)"
                    }
                  },
                  "content": {
                    "label": {
                      "component": "Box",
                      "display": "flex",
                      "alignItems": "center",
                      "gap": 0.5,
                      "marginBottom": "8px",
                      "elements": [
                        {
                          "component": "SvgIcon",
                          "icon": "ArrowBack",
                          "fontSize": "small",
                          "color": "primary"
                        },
                        {
                          "component": "Typography",
                          "variant": "caption",
                          "text": "Previous Post",
                          "styling": {
                            "color": "text.secondary",
                            "textTransform": "uppercase",
                            "fontWeight": 600,
                            "letterSpacing": "0.5px"
                          }
                        }
                      ]
                    },
                    "title": {
                      "component": "Typography",
                      "variant": "body1",
                      "text": "Previous Post Title Here",
                      "styling": {
                        "fontWeight": 600,
                        "color": "primary.main"
                      }
                    }
                  }
                }
              },
              {
                "gridItem": {
                  "xs": 12,
                  "sm": 6
                },
                "button": {
                  "component": "Card",
                  "clickable": true,
                  "styling": {
                    "background": "rgba(255, 255, 255, 0.6)",
                    "backdropFilter": "blur(20px)",
                    "borderRadius": "16px",
                    "padding": "20px",
                    "cursor": "pointer",
                    "transition": "all 0.3s",
                    "textAlign": "right",
                    "hover": {
                      "background": "rgba(255, 255, 255, 0.8)",
                      "transform": "translateX(4px)"
                    }
                  },
                  "content": {
                    "label": {
                      "component": "Box",
                      "display": "flex",
                      "alignItems": "center",
                      "justifyContent": "flex-end",
                      "gap": 0.5,
                      "marginBottom": "8px",
                      "elements": [
                        {
                          "component": "Typography",
                          "variant": "caption",
                          "text": "Next Post",
                          "styling": {
                            "color": "text.secondary",
                            "textTransform": "uppercase",
                            "fontWeight": 600,
                            "letterSpacing": "0.5px"
                          }
                        },
                        {
                          "component": "SvgIcon",
                          "icon": "ArrowForward",
                          "fontSize": "small",
                          "color": "primary"
                        }
                      ]
                    },
                    "title": {
                      "component": "Typography",
                      "variant": "body1",
                      "text": "Next Post Title Here",
                      "styling": {
                        "fontWeight": 600,
                        "color": "primary.main"
                      }
                    }
                  }
                }
              }
            ]
          }
        }
      }
    ]
  },
  "features": {
    "readingProgress": {
      "type": "linear-progress-bar",
      "updates": "on-scroll",
      "calculation": "scroll-percentage-of-article"
    },
    "tableOfContents": {
      "type": "auto-generated-from-headings",
      "behavior": "sticky-sidebar",
      "activeTracking": "scroll-spy",
      "smoothScroll": true
    },
    "codeBlocks": {
      "syntaxHighlighting": "prism or shiki",
      "copyButton": true,
      "languageIndicator": true,
      "lineNumbers": "optional"
    },
    "imageHandling": {
      "lazyLoading": true,
      "lightbox": "click-to-zoom",
      "captions": true,
      "optimization": "next/image"
    },
    "socialSharing": {
      "platforms": ["Twitter", "LinkedIn", "CopyLink"],
      "generateShareText": true,
      "trackShares": "optional-analytics"
    }
  },
  "seo": {
    "metaTags": {
      "title": "post-title | Ronnie Lutaro",
      "description": "post-excerpt",
      "ogImage": "post-featured-image",
      "ogType": "article",
      "twitterCard": "summary_large_image"
    },
    "structuredData": {
      "type": "Article",
      "schema": "JSON-LD"
    }
  },
  "accessibility": {
    "headingHierarchy": "proper-h1-h6-structure",
    "skipLinks": "skip-to-content",
    "focusManagement": "maintain-on-toc-click",
    "ariaLabels": "all-interactive-elements",
    "imageAltText": "required"
  },
  "responsive": {
    "mobile": {
      "toc": "hidden",
      "shareSidebar": "hidden",
      "shareActions": "fixed-bottom-bar",
      "fontSize": "16px-base"
    },
    "desktop": {
      "layout": "three-column",
      "toc": "sticky-left-sidebar",
      "share": "sticky-right-sidebar"
    }
  }
}
